scalene/README.md
scalene/__init__.py
scalene/__main__.py
scalene/adaptive.py
scalene/find_browser.py
scalene/get_line_atomic.cp313-win_amd64.pyd
scalene/get_module_details.py
scalene/launchbrowser.py
scalene/libscalene.dll
scalene/merge_scalene_neuron_profiles.py
scalene/profile.py
scalene/pywhere.cp313-win_amd64.pyd
scalene/redirect_python.py
scalene/replacement_exec.py
scalene/replacement_exit.py
scalene/replacement_fork.py
scalene/replacement_get_context.py
scalene/replacement_lock.py
scalene/replacement_mp_lock.py
scalene/replacement_pjoin.py
scalene/replacement_poll_selector.py
scalene/replacement_sem_lock.py
scalene/replacement_signal_fns.py
scalene/replacement_thread_join.py
scalene/runningstats.py
scalene/scalene-usage.txt
scalene/scalene_accelerator.py
scalene/scalene_analysis.py
scalene/scalene_apple_gpu.py
scalene/scalene_arguments.py
scalene/scalene_client_timer.py
scalene/scalene_config.py
scalene/scalene_cpu_profiler.py
scalene/scalene_funcutils.py
scalene/scalene_jax.py
scalene/scalene_json.py
scalene/scalene_jupyter.py
scalene/scalene_leak_analysis.py
scalene/scalene_library_profiler.py
scalene/scalene_library_registry.py
scalene/scalene_lifecycle.py
scalene/scalene_magics.py
scalene/scalene_mapfile.py
scalene/scalene_memory_profiler.py
scalene/scalene_neuron.py
scalene/scalene_nvidia_gpu.py
scalene/scalene_output.py
scalene/scalene_parseargs.py
scalene/scalene_preload.py
scalene/scalene_profiler.py
scalene/scalene_signal_manager.py
scalene/scalene_signals.py
scalene/scalene_sigqueue.py
scalene/scalene_statistics.py
scalene/scalene_tensorflow.py
scalene/scalene_torch.py
scalene/scalene_tracer.py
scalene/scalene_tracing.py
scalene/scalene_utility.py
scalene/scalene_windows.py
scalene/set_nvidia_gpu_modes.py
scalene/sorted_reservoir.py
scalene/sparkline.py
scalene/syntaxline.py
scalene/time_info.py
scalene/scalene-gui/README.md
scalene/scalene-gui/TODO-TypeScript.md
scalene/scalene-gui/amazon.ts
scalene/scalene-gui/anthropic.ts
scalene-2.1.3.dist-info/licenses/LICENSE
scalene-2.1.3.dist-info/METADATA
scalene-2.1.3.dist-info/WHEEL
scalene-2.1.3.dist-info/entry_points.txt
scalene-2.1.3.dist-info/top_level.txt
scalene-2.1.3.dist-info/RECORD
