Metadata-Version: 2.4
Name: scalene
Version: 2.1.3
Summary: Scalene: A high-resolution, low-overhead CPU, GPU, and memory profiler for Python with AI-powered optimization suggestions
Author-email: Emery Berger <emery@cs.umass.edu>, Sam Stern <jstern@umass.edu>, Juan Altmayer Pizzorno <juan@altmayer.com>
Project-URL: Homepage, https://github.com/plasma-umass/scalene
Project-URL: Repository, https://github.com/plasma-umass/scalene
Keywords: performance,profiler,optimization,CPU,GPU,memory,LLM
Classifier: Development Status :: 5 - Production/Stable
Classifier: Framework :: IPython
Classifier: Framework :: Jupyter
Classifier: Intended Audience :: Developers
Classifier: Intended Audience :: Science/Research
Classifier: Topic :: Software Development
Classifier: Topic :: Software Development :: Debuggers
Classifier: Programming Language :: Python
Classifier: Programming Language :: Python :: 3 :: Only
Classifier: Programming Language :: Python :: 3
Classifier: Programming Language :: Python :: 3.8
Classifier: Programming Language :: Python :: 3.9
Classifier: Programming Language :: Python :: 3.10
Classifier: Programming Language :: Python :: 3.11
Classifier: Programming Language :: Python :: 3.12
Classifier: Programming Language :: Python :: 3.13
Classifier: Programming Language :: Python :: 3.14
Classifier: License :: OSI Approved :: Apache Software License
Classifier: Operating System :: POSIX :: Linux
Classifier: Operating System :: MacOS :: MacOS X
Classifier: Operating System :: Microsoft :: Windows
Requires-Python: !=3.11.0,>=3.8
License-File: LICENSE
Requires-Dist: rich>=10.7.0
Requires-Dist: cloudpickle>=2.2.1
Requires-Dist: nvidia-ml-py>=12.555.43; platform_system != "Darwin"
Requires-Dist: Jinja2>=3.0.3
Requires-Dist: psutil>=5.9.2
Requires-Dist: numpy!=1.27,>=1.24.0; python_version < "3.14"
Requires-Dist: numpy>=2.3.4; python_version >= "3.14"
Requires-Dist: astunparse>=1.6.3; python_version < "3.9"
Requires-Dist: pydantic>=2.6
Requires-Dist: pyyaml>=6.0
Provides-Extra: test
Requires-Dist: pytest>=7.0; extra == "test"
Requires-Dist: pytest-asyncio>=0.21; extra == "test"
Requires-Dist: hypothesis>=6.0; extra == "test"
Requires-Dist: tensorflow>=2.15; (python_version < "3.14" and platform_system != "Windows") and extra == "test"
Requires-Dist: jax>=0.4.20; (python_version < "3.14" and platform_system != "Windows") and extra == "test"
Requires-Dist: jaxlib>=0.4.20; (python_version < "3.14" and platform_system != "Windows") and extra == "test"
Dynamic: license-file
